dfencoder/__init__.py
dfencoder/autoencoder.py
dfencoder/dataframe.py
dfencoder/logging.py
dfencoder/scalers.py
dfencoder-0.0.42.dist-info/LICENSE.txt
dfencoder-0.0.42.dist-info/METADATA
dfencoder-0.0.42.dist-info/WHEEL
dfencoder-0.0.42.dist-info/top_level.txt
dfencoder-0.0.42.dist-info/RECORD
